{
    "version": "https://jsonfeed.org/version/1",
    "title": "新浪财经新闻",
    "home_page_url": "https://news.dengchangdong.com/",
    "feed_url": "https://news.dengchangdong.com/rss.json",
    "description": "新浪最新财经新闻100条",
    "items": [
        {
            "id": 2230830,
            "content_html": "",
            "title": "【沈阳化工：下修业绩预告 因下游糊树脂手套需求锐减】沈阳化工(000698)7月6日晚间公告下修业绩预告：预计上半年盈利3.5亿元-4.3亿元，此前预计盈利4.3亿元-6亿元；公司上年同期亏损1.96亿元。沈阳化工表示，二季度下游糊树脂手套需求锐减，公司糊树脂产品的市场需求和价格大幅降低，产品盈利情况相比第一季度明显下降，未达到预期。",
            "date_modified": "2021-07-06T09:38:32.000Z"
        },
        {
            "id": 2230829,
            "content_html": "",
            "url": "https://finance.sina.cn/7x24/2021-07-06/detail-ikqciyzk3892071.d.html",
            "title": "【南向资金净卖出15.69亿港元 腾讯控股净卖出超10亿港元】南向资金今日净卖出15.69亿港元，连续3日净卖出。腾讯控股、舜宇光学科技、中芯国际分别遭净卖出10.06亿港元、3.62亿港元、3.09亿港元；中国海洋石油逆势获净买入2.64亿港元。",
            "date_modified": "2021-07-06T09:38:12.000Z"
        },
        {
            "id": 2230828,
            "content_html": "",
            "url": "https://finance.sina.cn/7x24/2021-07-06/detail-ikqciyzk3892023.d.html",
            "title": "博汇股份：持股4.22%股东洪淼松拟清仓减持。",
            "date_modified": "2021-07-06T09:37:58.000Z"
        },
        {
            "id": 2230827,
            "content_html": "",
            "url": "https://finance.sina.cn/7x24/2021-07-06/detail-ikqcfnca5291433.d.html",
            "title": "英镑兑美元刷新日低至1.3834，日内转跌0.04%。",
            "date_modified": "2021-07-06T09:37:22.000Z"
        },
        {
            "id": 2230826,
            "content_html": "",
            "url": "https://finance.sina.cn/7x24/2021-07-06/detail-ikqcfnca5291348.d.html",
            "title": "国金证券：公司收到中国证监会复函，据该复函，中国证监会对公司试点开展基金投资顾问业务无异议。",
            "date_modified": "2021-07-06T09:36:54.000Z"
        },
        {
            "id": 2230825,
            "content_html": "",
            "url": "https://finance.sina.cn/7x24/2021-07-06/detail-ikqciyzk3891754.d.html",
            "title": "近期赴美上市中概股盘前普跌，普普文化(CPOP.O)跌5.81%，叮咚买菜(DDL.N)跌5.03%，每日优鲜(MF.O)跌3.84%。",
            "date_modified": "2021-07-06T09:36:37.000Z"
        },
        {
            "id": 2230824,
            "content_html": "",
            "title": "【财政部印发[《农村环境整治资金管理办法》】 据财政部网站消息，为加强农村环境整治资金使用管理，财政部日前制定并印发了《农村环境整治资金管理办法》。根据办法，整治资金支持范围包括：农村生活垃圾治理，生活污水、黑臭水体治理，饮用水水源地环境保护和水源涵养和其他需要支持的事项，整治资金实施期限到2025年。",
            "date_modified": "2021-07-06T09:36:12.000Z"
        },
        {
            "id": 2230823,
            "content_html": "",
            "url": "https://finance.sina.cn/7x24/2021-07-06/detail-ikqciyzk3891576.d.html",
            "title": "据悉，西部利得基金申请的西部利得碳中和混合已经获批，这将成为市场上首只名称中含有“碳中和”字样的公募基金产品。（上证报）",
            "date_modified": "2021-07-06T09:35:32.000Z"
        },
        {
            "id": 2230822,
            "content_html": "",
            "url": "https://finance.sina.cn/7x24/2021-07-06/detail-ikqciyzk3891385.d.html",
            "title": "意大利经济部长：意大利经济将在2022年第三季度恢复到疫情前的水平。",
            "date_modified": "2021-07-06T09:34:48.000Z"
        },
        {
            "id": 2230821,
            "content_html": "",
            "url": "https://finance.sina.cn/7x24/2021-07-06/detail-ikqciyzk3891055.d.html",
            "title": "奔驰预计芯片短缺将影响第三和第四季度的销售情况。",
            "date_modified": "2021-07-06T09:33:22.000Z"
        },
        {
            "id": 2230820,
            "content_html": "",
            "url": "https://finance.sina.cn/7x24/2021-07-06/detail-ikqcfnca5290210.d.html",
            "title": "  梅赛德斯奔驰：第二季度销量为581,201辆，同比增长27%。",
            "date_modified": "2021-07-06T09:31:22.000Z"
        },
        {
            "id": 2230819,
            "content_html": "",
            "url": "https://finance.sina.cn/7x24/2021-07-06/detail-ikqciyzk3890597.d.html",
            "title": "【央行营业管理部：辖内相关机构不得为虚拟货币活动提供各种服务】今日，中国人民银行营业管理部、北京市地方金融监督管理局联合发布《关于防范虚拟货币交易活动的风险提示》。提示指出，对涉嫌为虚拟货币交易提供软件服务的北京取道文化发展有限公司予以清理整顿，责令该公司注销，目前该公司官方网站已停用。公告内警告辖内相关机构，不得为虚拟货币相关业务活动提供经营场所、商业展示、营销宣传、付费导流等服务。辖内金融机构、支付机构不得直接或间接为客户提供虚拟货币相关服务。同时提醒广大消费者，应增强风险意识，树立正确的投资理念。不参与虚拟货币交易炒作活动，不盲目跟风虚拟货币相关投机行为，谨防个人财产及权益受损。",
            "date_modified": "2021-07-06T09:31:08.000Z"
        },
        {
            "id": 2230818,
            "content_html": "",
            "url": "https://finance.sina.cn/7x24/2021-07-06/detail-ikqcfnca5290004.d.html",
            "title": "北向资金今日大幅净卖出0.6亿元。士兰微、中国中免、水井坊分别获净卖出3.63亿元、3.56亿元、3.48亿元。恒瑞医药净买入额居首，金额为2.46亿元。",
            "date_modified": "2021-07-06T09:30:33.000Z"
        },
        {
            "id": 2230817,
            "content_html": "",
            "url": "https://finance.sina.cn/7x24/2021-07-06/detail-ikqcfnca5289871.d.html",
            "title": "意大利经济部长：GDP增长可能超过5%。",
            "date_modified": "2021-07-06T09:30:20.000Z"
        },
        {
            "id": 2230816,
            "content_html": "",
            "url": "https://finance.sina.cn/7x24/2021-07-06/detail-ikqcfnca5289823.d.html",
            "title": "首批9只科创创业ETF已有8只上市。其中易方达科创创业ETF表现最为突出，昨日成交高达16.14亿元，位居同类及全市场股票ETF榜首；今日成交再达13.36亿元，成交量连续两日蝉联同类第一。",
            "date_modified": "2021-07-06T09:30:14.000Z"
        },
        {
            "id": 2230815,
            "content_html": "",
            "url": "https://finance.sina.cn/7x24/2021-07-06/detail-ikqciyzk3890256.d.html",
            "title": "  沈阳化工下修业绩预告：预计上半年盈利3.5亿元-4.3亿元，此前预计盈利4.3亿元-6亿元；第二季度下游糊树脂手套需求锐减，公司糊树脂产品的市场需求和价格大幅降低，产品盈利情况相比第一季度明显下降，未达到预期。",
            "date_modified": "2021-07-06T09:30:03.000Z"
        },
        {
            "id": 2230813,
            "content_html": "",
            "url": "https://finance.sina.cn/7x24/2021-07-06/detail-ikqcfnca5289126.d.html",
            "title": "  仁和药业：拟以7.2亿元的价格收购深圳市三浦天然化妆品有限公司等七家公司各80%股权。",
            "date_modified": "2021-07-06T09:26:45.000Z"
        },
        {
            "id": 2230812,
            "content_html": "",
            "url": "https://finance.sina.cn/7x24/2021-07-06/detail-ikqcfnca5288933.d.html",
            "title": "  东方锆业：预计上半年盈利5000万元-7000万元，上年同期亏损4745.8万元；报告期内，公司主营产品价格逐渐提升，2020年度公司增加的新业务（国富锆钛精选厂、焦作东锆新材料有限公司等）逐渐释放产能。",
            "date_modified": "2021-07-06T09:25:45.000Z"
        },
        {
            "id": 2230811,
            "content_html": "",
            "url": "https://finance.sina.cn/7x24/2021-07-06/detail-ikqcfnca5288731.d.html",
            "title": "北爱尔兰民主统一党（DUP）下一任领导人唐纳森计划在秋季进行更彻底的改革。",
            "date_modified": "2021-07-06T09:24:55.000Z"
        },
        {
            "id": 2230810,
            "content_html": "",
            "url": "https://finance.sina.cn/7x24/2021-07-06/detail-ikqcfnca5288161.d.html",
            "title": "惠誉：主权评级行动在上半年停滞。",
            "date_modified": "2021-07-06T09:22:23.000Z"
        },
        {
            "id": 2230809,
            "content_html": "",
            "url": "https://finance.sina.cn/7x24/2021-07-06/detail-ikqciyzk3888447.d.html",
            "title": "沙特将8月份售往亚洲的阿拉伯轻质原油官方售价定为较阿曼迪拜均价升水2.7美元。",
            "date_modified": "2021-07-06T09:21:31.000Z"
        },
        {
            "id": 2230808,
            "content_html": "",
            "url": "https://finance.sina.cn/7x24/2021-07-06/detail-ikqcfnca5287920.d.html",
            "title": "【中天精装：公司业务已进入60多个城市】中天精装(002989)在互动平台表示，公司业务已进入60多个城市，取得阶段性的初步进展。公司的百城计划正全力贯彻执行之中。到目前为止，除黑龙江、内蒙古、西藏、港澳台外，其余省份均已完成覆盖，后续会根据团队建设及客户情况继续加密、深耕。",
            "date_modified": "2021-07-06T09:21:21.000Z"
        },
        {
            "id": 2230807,
            "content_html": "",
            "url": "https://finance.sina.cn/7x24/2021-07-06/detail-ikqciyzk3888291.d.html",
            "title": "  日播时尚：合计持股18.75%股东王卫东、曲江亭拟合计减持不超过2%。",
            "date_modified": "2021-07-06T09:20:54.000Z"
        },
        {
            "id": 2230806,
            "content_html": "",
            "url": "https://finance.sina.cn/7x24/2021-07-06/detail-ikqcfnca5287611.d.html",
            "title": "  【中通客车：上半年销量同比下降34.96%】中通客车披露2021年6月份产销数据，当月实现产量1023辆、销量873辆；2021年1-6月，累计实现产量4041辆，同比下降29.12%，累计实现销量3841辆，同比下降34.96%。",
            "date_modified": "2021-07-06T09:20:03.000Z"
        },
        {
            "id": 2230805,
            "content_html": "",
            "url": "https://finance.sina.cn/7x24/2021-07-06/detail-ikqciyzk3887933.d.html",
            "title": "英国金融行为监管局：在决定是否需要采取进一步的监管行动之前，将在未来12-18个月内再次审查这些基金。",
            "date_modified": "2021-07-06T09:19:28.000Z"
        },
        {
            "id": 2230804,
            "content_html": "",
            "url": "https://finance.sina.cn/7x24/2021-07-06/detail-ikqciyzk3887841.d.html",
            "title": "  吉电股份：预计上半年盈利6.84亿元-7.24亿元，同比增长47.73%-56.36%，新能源发电量同比增长率超40%。",
            "date_modified": "2021-07-06T09:18:58.000Z"
        },
        {
            "id": 2230803,
            "content_html": "",
            "url": "https://finance.sina.cn/7x24/2021-07-06/detail-ikqcfnca5287193.d.html",
            "title": "英国金融行为监管局：基金经理们未能对其管理的基金价值进行评估。",
            "date_modified": "2021-07-06T09:17:24.000Z"
        },
        {
            "id": 2230802,
            "content_html": "",
            "url": "https://finance.sina.cn/7x24/2021-07-06/detail-ikqciyzk3887541.d.html",
            "title": "  【华致酒行：预计上半年净利同比增长65%-75%】华致酒行公告，预计上半年盈利3.5亿元-3.7亿元，同比增长65%-75%；直供终端门店和华致连锁门店的数量和质量稳步提升，客户黏性进一步提升，分销能力显著提高，销售收入同比大幅增长。",
            "date_modified": "2021-07-06T09:17:05.000Z"
        },
        {
            "id": 2230801,
            "content_html": "",
            "url": "https://finance.sina.cn/7x24/2021-07-06/detail-ikqciyzk3887451.d.html",
            "title": "吉利汽车：6月总销量为100163部，较去年同期减少约9%。",
            "date_modified": "2021-07-06T09:16:33.000Z"
        },
        {
            "id": 2230800,
            "content_html": "",
            "url": "https://finance.sina.cn/7x24/2021-07-06/detail-ikqciyzk3887307.d.html",
            "title": "意大利经济部长：预计第二季度意大利GDP增长约2%。",
            "date_modified": "2021-07-06T09:15:48.000Z"
        },
        {
            "id": 2230799,
            "content_html": "",
            "url": "https://finance.sina.cn/7x24/2021-07-06/detail-ikqciyzk3887174.d.html",
            "title": "印尼报告新增31189例新冠肺炎确诊病例，新增728例死亡病例。",
            "date_modified": "2021-07-06T09:15:17.000Z"
        },
        {
            "id": 2230798,
            "content_html": "",
            "url": "https://finance.sina.cn/7x24/2021-07-06/detail-ikqciyzk3887081.d.html",
            "title": "【通策医疗跌停 机构净卖出超2亿元】通策医疗今日跌停，龙虎榜数据显示，沪股通买入1.57亿元并卖出1.57亿元，四机构合计买入1.83亿元，两机构合计卖出3.87亿元。",
            "date_modified": "2021-07-06T09:14:42.000Z"
        },
        {
            "id": 2230797,
            "content_html": "",
            "url": "https://finance.sina.cn/7x24/2021-07-06/detail-ikqcfnca5286607.d.html",
            "title": "以太坊短线走低50美元，现报2304美元/枚。",
            "date_modified": "2021-07-06T09:13:51.000Z"
        },
        {
            "id": 2230796,
            "content_html": "",
            "url": "https://finance.sina.cn/7x24/2021-07-06/detail-ikqciyzk3886864.d.html",
            "title": "比特币短线下挫500美元，现报34611美元/枚。以太坊短线走低50美元，现报2304美元/枚。",
            "date_modified": "2021-07-06T09:13:24.000Z"
        },
        {
            "id": 2230795,
            "content_html": "",
            "url": "https://finance.sina.cn/7x24/2021-07-06/detail-ikqciyzk3886824.d.html",
            "title": "【会稽山：有销售糟烧白酒等副产品的传统】会稽山(601579)在互动平台表示，公司主营黄酒的生产、销售和研发，同时也利用黄酒生产过程产生的醪糟作为原料，通过蒸馏等技术生产糟烧白酒，并一直有销售糟烧白酒等副产品的传统，所占公司主营业务收入的比重较小。",
            "date_modified": "2021-07-06T09:13:10.000Z"
        },
        {
            "id": 2230794,
            "content_html": "",
            "url": "https://finance.sina.cn/7x24/2021-07-06/detail-ikqcfnca5286387.d.html",
            "title": "中国央行：近期，北京市地方金融监督管理局联合中国人民银行营业管理部、怀柔区政府相关部门，对涉嫌为虚拟货币交易提供软件服务的北京取道文化发展有限公司予以清理整顿，责令该公司注销，官方网站已停用。",
            "date_modified": "2021-07-06T09:12:28.000Z"
        },
        {
            "id": 2230793,
            "content_html": "",
            "url": "https://finance.sina.cn/7x24/2021-07-06/detail-ikqcfnca5286244.d.html",
            "title": "  【双良节能：获40对棒还原炉设备的采购订单 涉及金额近1.6亿元】双良节能公告，公司与青海丽豪半导体材料有限公司于2021年7月6日签订了《还原炉买卖合同》，本合同标的为买方采购的40对棒还原炉设备，合同金额1.5984亿元。据悉，合同签订210天内分批交货完毕，具体将以买方通知为准。本合同若顺利履行将对未来业绩有一定积极影响。",
            "date_modified": "2021-07-06T09:11:40.000Z"
        },
        {
            "id": 2230792,
            "content_html": "",
            "url": "https://finance.sina.cn/7x24/2021-07-06/detail-ikqcfnca5286212.d.html",
            "title": "中国央行：提醒广大消费者，应增强风险意识，树立正确的投资理念。不参与虚拟货币交易炒作活动，不盲目跟风虚拟货币相关投机行为，谨防个人财产及权益受损。要珍惜个人银行账户，不用于虚拟货币账户充值和提现、购买和销售相关交易充值码以及划转相关交易资金等活动，防止违法使用和个人信息泄露。",
            "date_modified": "2021-07-06T09:11:31.000Z"
        },
        {
            "id": 2230791,
            "content_html": "",
            "url": "https://finance.sina.cn/7x24/2021-07-06/detail-ikqciyzk3886442.d.html",
            "title": "中国央行：我们郑重警告辖内相关机构，不得为虚拟货币相关业务活动提供经营场所、商业展示、营销宣传、付费导流等服务。辖内金融机构、支付机构不得直接或间接为客户提供虚拟货币相关服务。",
            "date_modified": "2021-07-06T09:11:25.000Z"
        },
        {
            "id": 2230790,
            "content_html": "",
            "url": "https://finance.sina.cn/7x24/2021-07-06/detail-ikqcfnca5285996.d.html",
            "title": "央行发布关于防范虚拟货币交易活动的风险提示：我们郑重警告辖内相关机构，不得为虚拟货币相关业务活动提供经营场所、商业展示、营销宣传、付费导流等服务。辖内金融机构、支付机构不得直接或间接为客户提供虚拟货币相关服务。",
            "date_modified": "2021-07-06T09:10:45.000Z"
        },
        {
            "id": 2230789,
            "content_html": "",
            "url": "https://finance.sina.cn/7x24/2021-07-06/detail-ikqciyzk3886228.d.html",
            "title": "  【中鼎股份：子公司成为比亚迪新能源平台项目批量供应商】中鼎股份公告，子公司中鼎减震成为比亚迪新能源平台项目底盘轻量化总成产品的批量供应商，本次项目生命周期为4年，生命周期总金额约为2.82亿元。",
            "date_modified": "2021-07-06T09:10:38.000Z"
        },
        {
            "id": 2230787,
            "content_html": "",
            "url": "https://finance.sina.cn/7x24/2021-07-06/detail-ikqciyzk3885918.d.html",
            "title": "  【安凯客车：上半年销量同比下降22.33%】安凯客车披露2021年6月份产销情况，当前实现产量399辆、销量455辆；2021年1-6月，累计实现产量1587辆，同比下降24.43%，累计实现销量1586辆，同比下降22.33%。",
            "date_modified": "2021-07-06T09:09:47.000Z"
        },
        {
            "id": 2230785,
            "content_html": "",
            "url": "https://finance.sina.cn/7x24/2021-07-06/detail-ikqcfnca5285625.d.html",
            "title": "  【长海股份：预计上半年净利同比增长86%-118%】长海股份公告，预计上半年盈利2.3亿元-2.7亿元，同比增长85.81%-118.12%；报告期内，玻纤行业高景气延续，国内外玻璃纤维及制品市场需求旺盛，销售量价齐升，生产效率显著提升等因素业绩得以提升。",
            "date_modified": "2021-07-06T09:09:33.000Z"
        },
        {
            "id": 2230784,
            "content_html": "",
            "url": "https://finance.sina.cn/7x24/2021-07-06/detail-ikqciyzk3885668.d.html",
            "title": "【IDC：中国企业团队协作软件继续保持高速增长】2020年，新冠疫情爆发严重影响了企业和员工的正常办公和生活，但也为企业团队协作软件带来了前所未有的机遇。IDC《2020年中国企业团队协同软件市场跟踪报告》显示，2020年中国企业团队协同软件市场规模为2.55亿美元，同比增长31.8%。IDC预测，到2025年，中国企业团队协同软件市场规模将达到6.02亿美元，未来5年整体市场年复合增长率（CAGR）为18.8%。",
            "date_modified": "2021-07-06T09:08:34.000Z"
        },
        {
            "id": 2230783,
            "content_html": "",
            "url": "https://finance.sina.cn/7x24/2021-07-06/detail-ikqciyzk3885446.d.html",
            "title": "德国智库ZEW：虽然ZEW经济景气指数再次大幅下降，但仍然处于很高的水平。",
            "date_modified": "2021-07-06T09:07:27.000Z"
        },
        {
            "id": 2230782,
            "content_html": "",
            "url": "https://finance.sina.cn/7x24/2021-07-06/detail-ikqciyzk3885336.d.html",
            "title": "市场消息：沙特将8月份售往亚洲的阿拉伯轻质原油价格上调80美分/桶。",
            "date_modified": "2021-07-06T09:06:54.000Z"
        },
        {
            "id": 2230781,
            "content_html": "",
            "url": "https://finance.sina.cn/7x24/2021-07-06/detail-ikqciyzk3885286.d.html",
            "title": "  【俄外交部：俄美计划于7月底前举行战略稳定问题对话】当地时间7月6日，俄罗斯副外长里亚布科夫向外界透露，俄罗斯计划将在7月底前与美国就战略稳定问题举行初步对话。里亚布科夫说，到目前为止，俄方对计划举行的对话还没有头绪，但可以确定的是，对话将采取多部门联合会谈的形式。同时他强调，目前俄美间没有一个机制完善、机构合理的计划来处理战略稳定问题，俄方认为，对话应在不同层面上进行。里亚布科夫说，俄美间的战略稳定对话除了全体会议，还应设立专家工作组就具体问题进行分析。",
            "date_modified": "2021-07-06T09:06:39.000Z"
        },
        {
            "id": 2230780,
            "content_html": "",
            "url": "https://finance.sina.cn/7x24/2021-07-06/detail-ikqciyzk3885055.d.html",
            "title": "市场消息：沙特上调8月售往亚洲的石油价格。",
            "date_modified": "2021-07-06T09:05:30.000Z"
        },
        {
            "id": 2230779,
            "content_html": "",
            "url": "https://finance.sina.cn/7x24/2021-07-06/detail-ikqcfnca5284509.d.html",
            "title": "高盛：基本预期仍然是欧佩克+在2022第一季度前逐步增加产量，这最终将有助于满足其偏好，预计布伦特原油价格今年夏季将维持在80美元/桶。",
            "date_modified": "2021-07-06T09:04:12.000Z"
        },
        {
            "id": 2230778,
            "content_html": "",
            "url": "https://finance.sina.cn/7x24/2021-07-06/detail-ikqciyzk3884475.d.html",
            "title": "欧洲央行副行长金多斯：必须避免让暂时的通胀跳涨成为永久现象。",
            "date_modified": "2021-07-06T09:02:39.000Z"
        },
        {
            "id": 2230777,
            "content_html": "",
            "url": "https://finance.sina.cn/7x24/2021-07-06/detail-ikqciyzk3884351.d.html",
            "title": "德国智库ZEW：经济发展继续正常化。",
            "date_modified": "2021-07-06T09:02:03.000Z"
        },
        {
            "id": 2230776,
            "content_html": "",
            "url": "https://finance.sina.cn/7x24/2021-07-06/detail-ikqciyzk3884254.d.html",
            "title": "欧洲央行副行长金多斯：预计2021年下半年经济将强劲反弹。",
            "date_modified": "2021-07-06T09:01:32.000Z"
        },
        {
            "id": 2230775,
            "content_html": "",
            "url": "https://finance.sina.cn/7x24/2021-07-06/detail-ikqcfnca5283871.d.html",
            "title": "欧元区5月零售销售月率录得4.6%，创去年6月以来新高。",
            "date_modified": "2021-07-06T09:01:07.000Z"
        },
        {
            "id": 2230774,
            "content_html": "",
            "url": "https://finance.sina.cn/7x24/2021-07-06/detail-ikqcfnca5283781.d.html",
            "title": "德国7月ZEW经济景气指数录得63.3，创1月以来新低。",
            "date_modified": "2021-07-06T09:00:40.000Z"
        },
        {
            "id": 2230773,
            "content_html": "",
            "url": "https://finance.sina.cn/7x24/2021-07-06/detail-ikqciyzk3884050.d.html",
            "title": "   欧元区5月份零售销售同比增长9.0%，预期为8.2%。",
            "date_modified": "2021-07-06T09:00:30.000Z"
        },
        {
            "id": 2230772,
            "content_html": "",
            "url": "https://finance.sina.cn/7x24/2021-07-06/detail-ikqciyzk3883898.d.html",
            "title": "高盛：未达成协议给欧佩克+的原油生产路线带来了不确定性。",
            "date_modified": "2021-07-06T09:00:07.000Z"
        },
        {
            "id": 2230771,
            "content_html": "",
            "url": "https://finance.sina.cn/7x24/2021-07-06/detail-ikqcfnca5283438.d.html",
            "title": "  【郑州煤电：6对生产矿井目前已恢复生产】郑州煤电公告，截至本公告发布之日，公司所属6对生产矿井已全部完成整改并通过安全验收，目前已恢复生产。6对矿井核定生产能力合计825万吨/年。",
            "date_modified": "2021-07-06T08:59:06.000Z"
        },
        {
            "id": 2230770,
            "content_html": "",
            "url": "https://finance.sina.cn/7x24/2021-07-06/detail-ikqciyzk3883725.d.html",
            "title": "比特币上破35000美元/枚，日内涨3.84%。",
            "date_modified": "2021-07-06T08:58:44.000Z"
        },
        {
            "id": 2230768,
            "content_html": "",
            "url": "https://finance.sina.cn/7x24/2021-07-06/detail-ikqcfnca5282785.d.html",
            "title": "微芯生物：西奥罗尼治疗三阴性乳腺癌获得临床试验通知书。",
            "date_modified": "2021-07-06T08:55:21.000Z"
        },
        {
            "id": 2230767,
            "content_html": "",
            "url": "https://finance.sina.cn/7x24/2021-07-06/detail-ikqciyzk3882435.d.html",
            "title": "【山东海化：上半年预盈2.3亿至2.7亿元 同比扭亏】山东海化(000822)7月6日晚间发布业绩预告，预计2021年半年度净利2.3亿元-2.7亿元，公司上年同期亏损1.34亿元。报告期内，随着下游行业景气度回升，公司主导产品纯碱市场需求增加，销量及销价较上年同期均有较大幅度增长。",
            "date_modified": "2021-07-06T08:52:05.000Z"
        },
        {
            "id": 2230766,
            "content_html": "",
            "url": "https://finance.sina.cn/7x24/2021-07-06/detail-ikqcfnca5282104.d.html",
            "title": "  【成都路桥：联合体中标叶县西环路升级改造工程项目】成都路桥公告，2021年7月6日，公司收到叶县古城文化旅游投资有限公司发出的《中标通知书》，确定公司(牵头人)—中外建华诚工程技术集团有限公司(成员)联合体为叶县环路升级改造工程项目的中标单位，中标金额：总投资约4.867652亿元。",
            "date_modified": "2021-07-06T08:51:54.000Z"
        },
        {
            "id": 2230765,
            "content_html": "",
            "url": "https://finance.sina.cn/7x24/2021-07-06/detail-ikqcfnca5282074.d.html",
            "title": "【金域医学：君睿祺及君联茂林拟清仓减持不超71.95万股】金域医学公告，合计持股0.1555%的股东君睿祺及君联茂林拟自该公告发布之日起15个交易日后的3个月内，通过集中竞价方式合计减持公司股份不超过71.95万股，即不超过公司总股本的0.1555%。",
            "date_modified": "2021-07-06T08:51:42.000Z"
        },
        {
            "id": 2230764,
            "content_html": "",
            "url": "https://finance.sina.cn/7x24/2021-07-06/detail-ikqcfnca5281935.d.html",
            "title": "【Celsius CEO：明年或后年，以太坊的市值将完全超过比特币】加密借贷平台Celsius首席执行官兼联合创始人Alex Mashinsky表示，市值最大的加密货币比特币的市场主导地位已经开始输给以太坊，以太坊取代比特币成为世界上最有价值的加密货币的假设场景现在已经发生。他表示，Celsius管理着大约170亿美元的存款及客户的代币，而以美元计算排名第一的加密货币是以太坊。Mashinsky预测，到2022年或2023年，以太坊的市值将完全超过比特币。",
            "date_modified": "2021-07-06T08:51:01.000Z"
        },
        {
            "id": 2230763,
            "content_html": "",
            "url": "https://finance.sina.cn/7x24/2021-07-06/detail-ikqcfnca5281530.d.html",
            "title": "美国国家飓风中心：热带风暴“艾尔莎”（Elsa）正在佛罗里达群岛附近，佛罗里达西海岸部分地区已经发布了飓风警报。",
            "date_modified": "2021-07-06T08:49:34.000Z"
        },
        {
            "id": 2230762,
            "content_html": "",
            "url": "https://finance.sina.cn/7x24/2021-07-06/detail-ikqcfnca5281427.d.html",
            "title": "  【恒瑞医药：甲磺酸阿帕替尼片临床试验获批】恒瑞医药公告，甲磺酸阿帕替尼片获得药物临床试验批准通知书；子公司注射用HR20013获得药物临床试验批准通知书。",
            "date_modified": "2021-07-06T08:48:55.000Z"
        },
        {
            "id": 2230761,
            "content_html": "",
            "url": "https://finance.sina.cn/7x24/2021-07-06/detail-ikqcfnca5281413.d.html",
            "title": "【上半年100家房企融资6090亿，为2018年来最低水平】克而瑞研究中心发布的报告显示，2021年上半年100家典型房企的融资额为6090亿元，同比下降34%，环比下降29%，是2018年以来的最低水平。分季度来看，一季度融资额同环比双降，且仅高于2018年第三季度水平，二季度下降幅度更大。在“三道红线”出台叠加房贷集中度管理政策出台后，房企融资环境持续收紧，房企融资压力持续凸显，同时部分房企降杠杆意愿增强，整体融资量下降明显。（澎湃）",
            "date_modified": "2021-07-06T08:48:48.000Z"
        },
        {
            "id": 2230760,
            "content_html": "",
            "url": "https://finance.sina.cn/7x24/2021-07-06/detail-ikqcfnca5281223.d.html",
            "title": "美股区块链板块盘前走高，Bit Digital涨6.66%，MicroStrategy涨5.25%，亿邦国际涨3.83%，Riot Blockchain涨3.53%，第九城市涨3.26%，Marathon Patent涨3.17%，嘉楠科技涨2.32%。",
            "date_modified": "2021-07-06T08:47:31.000Z"
        },
        {
            "id": 2230759,
            "content_html": "",
            "url": "https://finance.sina.cn/7x24/2021-07-06/detail-ikqcfnca5281123.d.html",
            "title": "中国恒大2025年到期的8.75%美元票据每1美元面值跌3.9美分至60.7美分。",
            "date_modified": "2021-07-06T08:46:57.000Z"
        },
        {
            "id": 2230758,
            "content_html": "",
            "url": "https://finance.sina.cn/7x24/2021-07-06/detail-ikqcfnca5280979.d.html",
            "title": "【确诊6例 民航局对法国航空一航班实施熔断】据中国民航局官网消息，7月6日，民航局再发熔断指令，对法国航空公司AF382航班（巴黎至天津）实施熔断措施。根据民航局通报，6月25日入境的法国航空公司AF382航班（巴黎至天津）确诊新冠肺炎旅客6例。",
            "date_modified": "2021-07-06T08:46:10.000Z"
        },
        {
            "id": 2230757,
            "content_html": "",
            "url": "https://finance.sina.cn/7x24/2021-07-06/detail-ikqciyzk3880801.d.html",
            "title": "【苏宁易购现5.62亿元大宗交易】今日苏宁易购(002024)出现5.62亿元大宗交易，成交价格均为5.59元/股，卖出方均为机构席位，买入方为华泰证券股份有限公司南京中山东路华泰证券大厦证券营业部。苏宁易购今日收盘价为6.15元/股。",
            "date_modified": "2021-07-06T08:44:12.000Z"
        },
        {
            "id": 2230756,
            "content_html": "",
            "url": "https://finance.sina.cn/7x24/2021-07-06/detail-ikqciyzk3880419.d.html",
            "title": "英国预算责任办公室（OBR）：到2050年实现净零排放的净财政成本可能相对较低。",
            "date_modified": "2021-07-06T08:42:16.000Z"
        },
        {
            "id": 2230755,
            "content_html": "",
            "url": "https://finance.sina.cn/7x24/2021-07-06/detail-ikqcfnca5280059.d.html",
            "title": "【中钢国际：半年度净利预增59.31%-82.07%】中钢国际(000928)7月6日晚间发布业绩预告，预计2021年半年度净利3.5亿元-4亿元，同比增长59.31%-82.07%。上半年，公司国内外工程项目执行平顺，但钢材价格大幅上涨，项目毛利率较上年同期有所下降；公司持有的重庆钢铁股票增加公允价值1.8亿元，与上年同期的－9086.82万元相比有较大增长。",
            "date_modified": "2021-07-06T08:41:09.000Z"
        },
        {
            "id": 2230754,
            "content_html": "",
            "url": "https://finance.sina.cn/7x24/2021-07-06/detail-ikqcfnca5279690.d.html",
            "title": "  【山东海化：预计上半年盈利2.3亿元-2.7亿元 扭亏为盈】山东海化公告，预计上半年盈利2.3亿元-2.7亿元，上年同期亏损1.3亿元；报告期内公司主导产品纯碱市场需求增加，销量及销价较上年同期均有较大幅度增长。",
            "date_modified": "2021-07-06T08:40:05.000Z"
        },
        {
            "id": 2230753,
            "content_html": "",
            "url": "https://finance.sina.cn/7x24/2021-07-06/detail-ikqcfnca5279645.d.html",
            "title": "  【东宏股份：1.4亿元预中标保温管采购项目】东宏股份公告，预中标华能董家口电厂至新区西部城区长输管线项目所需保温管采购项目，中标金额1.4亿元。",
            "date_modified": "2021-07-06T08:39:54.000Z"
        },
        {
            "id": 2230752,
            "content_html": "",
            "url": "https://finance.sina.cn/7x24/2021-07-06/detail-ikqciyzk3879735.d.html",
            "title": "英国预算责任办公室（OBR）：英国财政面临“潜在灾难性的”风险。",
            "date_modified": "2021-07-06T08:39:28.000Z"
        },
        {
            "id": 2230751,
            "content_html": "",
            "url": "https://finance.sina.cn/7x24/2021-07-06/detail-ikqciyzk3879674.d.html",
            "title": "  【宁波港：上半年预计完成集装箱吞吐量同比增长22%】宁波港公告，6月预计完成集装箱吞吐量314万标准箱，同比增长13.4%；预计完成货物吞吐量8294万吨，同比下降0.2%。上半年预计完成集装箱吞吐量1766万标准箱，同比增长22.4%，预计完成货物吞吐量48579万吨，同比增长8.9%。",
            "date_modified": "2021-07-06T08:38:59.000Z"
        },
        {
            "id": 2230750,
            "content_html": "",
            "url": "https://finance.sina.cn/7x24/2021-07-06/detail-ikqciyzk3879499.d.html",
            "title": "英国预算责任办公室（OBR）：在早期行动方案中实现净零财政影响，将使2050-51年公共部门净债务增加GDP的21%。",
            "date_modified": "2021-07-06T08:37:56.000Z"
        },
        {
            "id": 2230749,
            "content_html": "",
            "url": "https://finance.sina.cn/7x24/2021-07-06/detail-ikqcfnca5279327.d.html",
            "title": "【泛亚微透：拟1.56亿元购买大音希声60%股权】泛亚微透(688386)7月6日晚间公告，拟1.56亿元购买上海大音希声新型材料有限公司（简称“大音希声”）60%的股权。大音希声目前业务以生产纳米孔气凝胶绝热毡为主。此次交易有助于做大做强气凝胶业务，通过资源整合，形成气凝胶产业在军用、民用高端领域快速增长。",
            "date_modified": "2021-07-06T08:37:47.000Z"
        },
        {
            "id": 2230748,
            "content_html": "",
            "url": "https://finance.sina.cn/7x24/2021-07-06/detail-ikqcfnca5279232.d.html",
            "title": "  【新奥股份：预计上半年净利润同比增长170%-190%】新奥股份公告，预计上半年净利润增加12.37亿元-13.8亿元，同比增长170%-190%；公司积极拓展海外进口直销气业务，直销气业务为公司业绩增长带来较大贡献，预计实现净利润约2.2亿元，同比增加约2.08亿元。",
            "date_modified": "2021-07-06T08:37:21.000Z"
        },
        {
            "id": 2230747,
            "content_html": "",
            "url": "https://finance.sina.cn/7x24/2021-07-06/detail-ikqciyzk3879206.d.html",
            "title": "英国预算责任办公室（OBR）：英国因新冠肺炎面临资金不足的支出压力。",
            "date_modified": "2021-07-06T08:36:25.000Z"
        },
        {
            "id": 2230745,
            "content_html": "",
            "url": "https://finance.sina.cn/7x24/2021-07-06/detail-ikqciyzk3878989.d.html",
            "title": "  【汉马科技：6月中重卡销量同比增长13.28%】汉马科技公告，6月中重卡销量2294辆，同比增长13.28%；上半年累计中重卡销量10773辆，同比增长15.295%。",
            "date_modified": "2021-07-06T08:35:14.000Z"
        },
        {
            "id": 2230744,
            "content_html": "",
            "url": "https://finance.sina.cn/7x24/2021-07-06/detail-ikqcfnca5278737.d.html",
            "title": "小鹏汽车美股盘前跌3.5%，报42.3美元。",
            "date_modified": "2021-07-06T08:34:53.000Z"
        },
        {
            "id": 2230743,
            "content_html": "",
            "url": "https://finance.sina.cn/7x24/2021-07-06/detail-ikqcfnca5278467.d.html",
            "title": "【立讯精密已成立芯片制造公司，注册资本3亿】天眼查App显示，7月2日，立芯精密智造（昆山）有限公司成立，注册资本3亿人民币，法定代表人为郝杰，经营范围含显示器件制造；工业机器人制造；智能机器人的研发；集成电路芯片及产品制造等。股东信息显示，该公司由立讯精密工业股份有限公司全资控股。",
            "date_modified": "2021-07-06T08:33:14.000Z"
        },
        {
            "id": 2230742,
            "content_html": "",
            "url": "https://finance.sina.cn/7x24/2021-07-06/detail-ikqciyzk3878557.d.html",
            "title": "意大利央行行长维斯科：不能排除意大利较小的银行发生危机的可能性，其中有一些银行非常脆弱。",
            "date_modified": "2021-07-06T08:32:34.000Z"
        },
        {
            "id": 2230741,
            "content_html": "",
            "url": "https://finance.sina.cn/7x24/2021-07-06/detail-ikqciyzk3878363.d.html",
            "title": "俄罗斯外交部：俄美关系正常化的机会是存在的，不应该错过，莫斯科已准备好为此付出努力。",
            "date_modified": "2021-07-06T08:31:37.000Z"
        },
        {
            "id": 2230740,
            "content_html": "",
            "url": "https://finance.sina.cn/7x24/2021-07-06/detail-ikqcfnca5278123.d.html",
            "title": "  【济川药业：子公司产品退出省级医保目录】济川药业公告，全资子公司产品蒲地蓝消炎口服液及蛋白琥珀酸铁口服溶液退出省级医保目录。",
            "date_modified": "2021-07-06T08:31:27.000Z"
        },
        {
            "id": 2230739,
            "content_html": "",
            "url": "https://finance.sina.cn/7x24/2021-07-06/detail-ikqcfnca5278088.d.html",
            "title": "在岸人民币兑美元7月6日16:30收盘报6.4627，较上一交易日下跌19点。",
            "date_modified": "2021-07-06T08:31:20.000Z"
        },
        {
            "id": 2230738,
            "content_html": "",
            "url": "https://finance.sina.cn/7x24/2021-07-06/detail-ikqciyzk3878274.d.html",
            "title": "意大利央行行长维斯科：2021年的平均经济增长率可能在5%左右。",
            "date_modified": "2021-07-06T08:31:03.000Z"
        },
        {
            "id": 2230737,
            "content_html": "",
            "url": "https://finance.sina.cn/7x24/2021-07-06/detail-ikqcfnca5277867.d.html",
            "title": "意大利央行行长维斯科：意大利央行正在评估可能的解决方案，以应对影响到大中型银行的危机。",
            "date_modified": "2021-07-06T08:30:28.000Z"
        },
        {
            "id": 2230736,
            "content_html": "",
            "url": "https://finance.sina.cn/7x24/2021-07-06/detail-ikqcfnca5277692.d.html",
            "title": "意大利央行行长维斯科：预计不良贷款将会增加，但不会比以往衰退后的增加规模更大。",
            "date_modified": "2021-07-06T08:30:06.000Z"
        },
        {
            "id": 2230735,
            "content_html": "",
            "url": "https://finance.sina.cn/7x24/2021-07-06/detail-ikqcfnca5277627.d.html",
            "title": "【泛亚微透：拟1.56亿元购买大音希声60%的股权】泛亚微透公告，拟使用自有资金1.56亿元购买大音希声60%的股权。本次交易完成后，公司持有大音希声60%的股权，大音希声将成为公司的控股子公司。",
            "date_modified": "2021-07-06T08:29:56.000Z"
        },
        {
            "id": 2230734,
            "content_html": "",
            "url": "https://finance.sina.cn/7x24/2021-07-06/detail-ikqcfnca5277516.d.html",
            "title": "  【金地集团：上半年签约额同比上升60.22%】金地集团公告，2021年6月，公司实现签约面积178.6万平方米，同比上升2.69%；实现签约金额340.3亿元，同比上升0.63%。2021年1-6月，公司累计实现签约面积753万平方米，同比上升55.27%；累计实现签约金额1628.3亿元，同比上升60.22%。",
            "date_modified": "2021-07-06T08:29:19.000Z"
        },
        {
            "id": 2230733,
            "content_html": "",
            "url": "https://finance.sina.cn/7x24/2021-07-06/detail-ikqciyzk3877699.d.html",
            "title": "【五矿稀土：6月末起部分稀土产品价格企稳回升】五矿稀土(000831)7月6日晚披露股票交易异常波动公告称，公司不存在应披露而未披露信息。公司大部分稀土产品价格于第一季度大幅上涨后整体回调，自6月末始，部分稀土产品价格企稳回升，稀土及相关行业上市公司关注度提升。",
            "date_modified": "2021-07-06T08:29:07.000Z"
        },
        {
            "id": 2230732,
            "content_html": "",
            "url": "https://finance.sina.cn/7x24/2021-07-06/detail-ikqciyzk3877455.d.html",
            "title": "俄罗斯副外长里亚布科夫：莫斯科方面希望在7月举行第一轮核战略稳定会谈。",
            "date_modified": "2021-07-06T08:27:12.000Z"
        },
        {
            "id": 2230731,
            "content_html": "",
            "url": "https://finance.sina.cn/7x24/2021-07-06/detail-ikqcfnca5277178.d.html",
            "title": "苏宁易购今日复牌涨停，盘后数据显示，深股通席位买入3519万元并卖出1296万元。",
            "date_modified": "2021-07-06T08:27:01.000Z"
        },
        {
            "id": 2230729,
            "content_html": "",
            "url": "https://finance.sina.cn/7x24/2021-07-06/detail-ikqciyzk3877243.d.html",
            "title": "【喜临门：上半年净利预增406%-417%】喜临门(603008)7月6日晚间披露业绩预告，上半年预盈2.15亿元至2.2亿元，同比增长406%到417%。上年同期因新冠肺炎疫情，公司生产经营和盈利能力受到一定影响，半年度基数偏低。本年度业务恢复正常，主营业务有序开展。",
            "date_modified": "2021-07-06T08:25:54.000Z"
        },
        {
            "id": 2230728,
            "content_html": "",
            "url": "https://finance.sina.cn/7x24/2021-07-06/detail-ikqcfnca5276952.d.html",
            "title": "  斗鱼美股盘前跌幅扩大至逾10%。",
            "date_modified": "2021-07-06T08:25:38.000Z"
        },
        {
            "id": 2230727,
            "content_html": "",
            "url": "https://finance.sina.cn/7x24/2021-07-06/detail-ikqciyzk3877164.d.html",
            "title": "【闻泰科技：安世半导体成立独立半导体设备公司ITEC】7月6日，闻泰科技全资子公司安世半导体宣布，总部位于荷兰奈梅亨，由飞利浦（现为Nexperia）于1991年创立的半导体设备制造商ITEC，今日宣布成为独立实体，但ITEC仍是Nexperia集团的一部分。ITEC致力为全球半导体制造商提供经久耐用的创新性制造解决方案。通过此举，ITEC能够及时解决第三方市场的问题，满足对半导体的喷井式需求。",
            "date_modified": "2021-07-06T08:25:31.000Z"
        },
        {
            "id": 2230726,
            "content_html": "",
            "url": "https://finance.sina.cn/7x24/2021-07-06/detail-ikqciyzk3877002.d.html",
            "title": "一个代表团的消息人士称，阿拉伯联合酋长国退出欧佩克+的问题不在议程上，欧佩克+协议的缔约方正在寻找解决方案。（卫星新闻）",
            "date_modified": "2021-07-06T08:24:42.000Z"
        },
        {
            "id": 2230725,
            "content_html": "",
            "url": "https://finance.sina.cn/7x24/2021-07-06/detail-ikqcfnca5276627.d.html",
            "title": "【国药中金“牵手”南昌工控基金等发展高端医疗器械产业】近日，国药中金与南昌工控投资基金管理公司、进贤县政府签署合作协议。国药中金将通过与南昌工控基金、进贤共同发起设立以创新医疗器械投资为主的二期基金，面向医疗器械科技产业园具有协同效应和创新能力的优质标的进行投资和赋能，合作推进高端医疗器械先进制造产业。",
            "date_modified": "2021-07-06T08:23:53.000Z"
        }
    ]
}